zzassertions/__init__.py
zzassertions/assertions.py
python_assertions-0.0.1.dist-info/LICENSE
python_assertions-0.0.1.dist-info/METADATA
python_assertions-0.0.1.dist-info/WHEEL
python_assertions-0.0.1.dist-info/top_level.txt
python_assertions-0.0.1.dist-info/RECORD
