Metadata-Version: 2.1
Name: python-assertions
Version: 0.0.1
Summary: Foo demo project the II
Home-page: https://github.com/zzirakadze/assertions-for-automated-testing.git
Author: Zura Zirakadze
Author-email: zirakadzez@gmail.com
License: MIT
Keywords: assertions,python
Classifier: Development Status :: 5 - Production/Stable
Classifier: License :: OSI Approved :: MIT License
Classifier: Programming Language :: Python :: 3.9
Classifier: Operating System :: OS Independent
License-File: LICENSE
